pyarr/__init__.py
pyarr/base.py
pyarr/const.py
pyarr/exceptions.py
pyarr/lib/__init__.py
pyarr/lib/alias_decorator.py
pyarr/lidarr.py
pyarr/models/__init__.py
pyarr/models/common.py
pyarr/models/lidarr.py
pyarr/models/radarr.py
pyarr/models/readarr.py
pyarr/models/sonarr.py
pyarr/py.typed
pyarr/radarr.py
pyarr/readarr.py
pyarr/request_handler.py
pyarr/sonarr.py
pyarr/types.py
pyarr-5.2.0.dist-info/LICENSE
pyarr-5.2.0.dist-info/METADATA
pyarr-5.2.0.dist-info/WHEEL
pyarr-5.2.0.dist-info/RECORD
