Metadata-Version: 2.1
Name: pyarr
Version: 5.2.0
Summary: Synchronous Sonarr, Radarr, Lidarr and Readarr API's for Python
Home-page: https://github.com/totaldebug/pyarr
License: MIT
Keywords: sonarr,radarr,readarr,lidarr,api,wrapper,plex
Author: Steven Marks
Author-email: marksie1988@users.noreply.github.com
Requires-Python: >=3.9,<4.0
Classifier: Development Status :: 5 - Production/Stable
Classifier: Intended Audience :: Developers
Classifier: License :: OSI Approved :: MIT License
Classifier: Natural Language :: English
Classifier: Programming Language :: Python :: 3
Classifier: Programming Language :: Python :: 3.9
Classifier: Programming Language :: Python :: 3.10
Classifier: Programming Language :: Python :: 3.11
Classifier: Topic :: Software Development :: Libraries :: Python Modules
Requires-Dist: overrides (>=7.3.1,<8.0.0)
Requires-Dist: requests (>=2.28.2,<3.0.0)
Requires-Dist: types-requests (>=2.28.11.17,<3.0.0.0)
Project-URL: Documentation, https://docs.totaldebug.uk/pyarr
Project-URL: Repository, https://github.com/totaldebug/pyarr
